{
  "accentColor": "{{appsmith.theme.colors.primaryColor}}",
  "allowDialCodeChange": false,
  "allowFormatting": true,
  "animateLoading": true,
  "autoFocus": false,
  "borderRadius": "{{appsmith.theme.borderRadius.appBorderRadius}}",
  "bottomRow": 53,
  "boxShadow": "none",
  "defaultDialCode": "+973",
  "defaultText": "",
  "dynamicBindingPathList": [
    {
      "key": "accentColor"
    },
    {
      "key": "borderRadius"
    }
  ],
  "dynamicHeight": "FIXED",
  "dynamicTriggerPathList": [],
  "iconAlign": "left",
  "isDisabled": false,
  "isLoading": false,
  "isRequired": true,
  "isVisible": true,
  "key": "yzs5jnsq9c",
  "label": "Label",
  "labelAlignment": "left",
  "labelPosition": "Top",
  "labelStyle": "",
  "labelTextSize": "0.875rem",
  "labelWidth": 5,
  "leftColumn": 2,
  "maxDynamicHeight": 9000,
  "minDynamicHeight": 4,
  "minWidth": 450,
  "mobileBottomRow": 45,
  "mobileLeftColumn": 3,
  "mobileRightColumn": 23,
  "mobileTopRow": 38,
  "needsErrorInfo": false,
  "originalBottomRow": 52,
  "originalTopRow": 45,
  "parentColumnSpace": 5.828125,
  "parentId": "7hp8dpwajm",
  "parentRowSpace": 10,
  "renderMode": "CANVAS",
  "resetOnSubmit": true,
  "responsiveBehavior": "fill",
  "rightColumn": 53,
  "topRow": 46,
  "type": "PHONE_INPUT_WIDGET",
  "version": 1,
  "widgetId": "seno18pkf0",
  "widgetName": "PhoneInput1"
}